README
mud
setup.py
data/test.txt
examples/hello_stacked.py
examples/hello_world.cgi
examples/hello_world.py
muex/__init__.py
muex/console.py
muex/cube.js
muex/cube.lsl
muex/cube.py
muex/draw.css
muex/draw.js
muex/draw.py
muex/edit.css
muex/edit.js
muex/edit.py
muex/hello_pantheon.js
muex/hello_pantheon.py
muex/jira.js
muex/jira.py
muex/logconsole.css
muex/logconsole.js
muex/logconsole.py
muex/login.py
muex/shellconsole.css
muex/shellconsole.js
muex/shellconsole.py
muex/sourceconsole.css
muex/sourceconsole.js
muex/sourceconsole.py
muex/testclient.js
muex/testclient.py
muex/testconsole.css
muex/testconsole.js
muex/testconsole.py
muex/twitter.css
muex/twitter.js
muex/twitter.py
mulib/__init__.py
mulib/auth.py
mulib/caps.py
mulib/cgiadapter.py
mulib/eventrouter.js
mulib/eventrouter.py
mulib/htmlexception.py
mulib/mu.py
mulib/mud.py
mulib/nodes.py
mulib/nodes_test.py
mulib/pantheon.js
mulib/pantheon.py
mulib/pantheon_test.py
mulib/proxy.py
mulib/resources.py
mulib/shaped.py
mulib/shaped_test.py
mulib/stacked.py
mulib/stacked_test.py
mulib/tests.py
mulib/virtual.py
mulib.egg-info/PKG-INFO
mulib.egg-info/SOURCES.txt
mulib.egg-info/dependency_links.txt
mulib.egg-info/requires.txt
mulib.egg-info/top_level.txt
