Metadata-Version: 1.0
Name: mulib
Version: 0.2
Summary: REST web service framework
Home-page: http://wiki.secondlife.com/wiki/Mulib
Author: Linden Lab
Author-email: eventletdev@lists.secondlife.com
License: UNKNOWN
Platform: UNKNOWN
Classifier: License :: OSI Approved :: MIT License
Classifier: Programming Language :: Python
Classifier: Topic :: Internet :: WWW/HTTP
Classifier: Topic :: Software Development :: Libraries :: Python Modules
Classifier: Intended Audience :: Developers
Classifier: Development Status :: 4 - Beta
